instarest/__init__.py
instarest/apps/__init__.py
instarest/apps/base.py
instarest/core/__init__.py
instarest/core/config.py
instarest/core/logging.py
instarest/crud/__init__.py
instarest/crud/base.py
instarest/db/__init__.py
instarest/db/base_class.py
instarest/db/init_db.py
instarest/db/session.py
instarest/dependencies.py
instarest/initializer.py
instarest/routers/__init__.py
instarest/routers/base.py
instarest/routers/rest.py
instarest/schemas/__init__.py
instarest/schemas/base.py
instarest/utils/__init__.py
instarest/utils/models.py
instarest-0.0.13.dist-info/LICENSE
instarest-0.0.13.dist-info/METADATA
instarest-0.0.13.dist-info/WHEEL
instarest-0.0.13.dist-info/RECORD
