Metadata-Version: 2.1
Name: instarest
Version: 0.0.13
Summary: Declarative, instant REST APIs based on FastAPI, Pydantic, SQLAlchemy, and PostgreSQL
Author: Eric Robinson
Requires-Python: >=3.11,<4.0
Classifier: Programming Language :: Python :: 3
Classifier: Programming Language :: Python :: 3.11
Requires-Dist: fastapi (>=0.100.1,<0.101.0)
Requires-Dist: fastapi-versioning (>=0.10.0,<0.11.0)
Requires-Dist: httpx (>=0.24.1,<0.25.0)
Requires-Dist: psycopg2-binary (>=2.9.6,<3.0.0)
Requires-Dist: pydantic (>=1.10.12,<2.0.0)
Requires-Dist: python-dotenv (>=1.0.0,<2.0.0)
Requires-Dist: sqlalchemy (>=2.0.15,<3.0.0)
Requires-Dist: uvicorn (>=0.23.0)
